odoo/addons/delivery_roulier_dpd_fr/README.rst
odoo/addons/delivery_roulier_dpd_fr/__init__.py
odoo/addons/delivery_roulier_dpd_fr/__manifest__.py
odoo/addons/delivery_roulier_dpd_fr/data/delivery_carrier.xml
odoo/addons/delivery_roulier_dpd_fr/data/product.product.xml
odoo/addons/delivery_roulier_dpd_fr/demo/carrier_account.xml
odoo/addons/delivery_roulier_dpd_fr/i18n/delivery_roulier_dpd_fr.pot
odoo/addons/delivery_roulier_dpd_fr/i18n/it.po
odoo/addons/delivery_roulier_dpd_fr/models/__init__.py
odoo/addons/delivery_roulier_dpd_fr/models/carrier_account.py
odoo/addons/delivery_roulier_dpd_fr/models/delivery_carrier.py
odoo/addons/delivery_roulier_dpd_fr/models/stock_picking.py
odoo/addons/delivery_roulier_dpd_fr/models/stock_quant_package.py
odoo/addons/delivery_roulier_dpd_fr/readme/CONFIGURE.rst
odoo/addons/delivery_roulier_dpd_fr/readme/CONTRIBUTORS.rst
odoo/addons/delivery_roulier_dpd_fr/readme/DESCRIPTION.rst
odoo/addons/delivery_roulier_dpd_fr/static/description/icon.png
odoo/addons/delivery_roulier_dpd_fr/static/description/index.html
odoo/addons/delivery_roulier_dpd_fr/views/carrier_account_views.xml
odoo_addon_delivery_roulier_dpd_fr-16.0.1.0.0.8.dist-info/METADATA
odoo_addon_delivery_roulier_dpd_fr-16.0.1.0.0.8.dist-info/WHEEL
odoo_addon_delivery_roulier_dpd_fr-16.0.1.0.0.8.dist-info/top_level.txt
odoo_addon_delivery_roulier_dpd_fr-16.0.1.0.0.8.dist-info/RECORD
