Metadata-Version: 2.1
Name: odoo-addon-delivery_roulier_dpd_fr
Version: 16.0.1.0.0.8
Summary: Generate Labels for DPD
Home-page: https://github.com/OCA/delivery-carrier
Author: Akretion, Odoo Community Association (OCA)
Author-email: support@odoo-community.org
License: AGPL-3
Classifier: Programming Language :: Python
Classifier: Framework :: Odoo
Classifier: Framework :: Odoo :: 16.0
Classifier: License :: OSI Approved :: GNU Affero General Public License v3
Requires-Python: >=3.10
Requires-Dist: cerberus
Requires-Dist: odoo-addon-delivery-roulier<16.1dev,>=16.0dev
Requires-Dist: odoo<16.1dev,>=16.0a
